bfpy_package_brainy7890/__init__.py
bfpy_package_brainy7890/main.py
bfpy_brainy-0.1.0.dist-info/METADATA
bfpy_brainy-0.1.0.dist-info/WHEEL
bfpy_brainy-0.1.0.dist-info/RECORD
