Metadata-Version: 2.4
Name: bfpy-brainy
Version: 0.1.0
Summary: A simple python package that interprets and compiles Brainfuck code.
Project-URL: Homepage, https://github.com/Brainy0789/BfPy
Project-URL: Issues, https://github.com/Brainy0789/BfPy/issues
Author: Brainy7890
License-Expression: MIT
Classifier: Operating System :: OS Independent
Classifier: Programming Language :: Python :: 3
Requires-Python: >=3.9
